fh_altair/__init__.py
tests/__init__.py
tests/test_basics.py
tests/test_clicker.py
fh_altair-0.0.2.dist-info/LICENSE
fh_altair-0.0.2.dist-info/METADATA
fh_altair-0.0.2.dist-info/WHEEL
fh_altair-0.0.2.dist-info/top_level.txt
fh_altair-0.0.2.dist-info/RECORD
