Metadata-Version: 2.1
Name: fh-altair
Version: 0.0.2
Summary: Make is easy to use altair in FastHTML
Author: Vincent D. Warmerdam
License-File: LICENSE
Requires-Dist: altair
Requires-Dist: python-fasthtml
Provides-Extra: dev
Requires-Dist: pytest ; extra == 'dev'
Requires-Dist: pandas ; extra == 'dev'
